{
  "$schema" : "https://json-schema.org/draft/2020-12/schema",
  "type" : "object",
  "description": "When written: when zooming in on a signal using the FSS scanner",
  "extends" : { "$ref": "../_Event.json"},
  "allOf": [{ "$ref": "../_Event.json"}],
  "properties" : {
    "SystemAddress" : {
      "title" : "SystemAddress",
      "type" : "integer",
      "examples" : [ 198875014308, 3657265287866, 6955800204002 ]
    },
    "SignalName" : {
      "title" : "SignalName",
      "type" : "string",
      "examples" : [ "$MULTIPLAYER_SCENARIO42_TITLE;", "$ListeningPost:#index=1;", "BLUE TYPHOON Q1M-83F" ]
    },
    "SignalType" : {
      "title" : "SignalType",
      "type" : "string",
      "examples" : [ "USS", "TouristBeacon" ]
    },
    "SignalName_Localised" : {
      "title" : "SignalName_Localised",
      "type" : "string",
      "examples" : [ "Nav Beacon", "Listening Post", "Conflict Zone [Low Intensity]" ]
    },
    "IsStation" : {
      "title" : "IsStation",
      "description": "If it is a station",
      "type" : "boolean",
      "examples" : [ true ]
    },
    "USSType" : {
      "title" : "USSType",
      "description": "If a Unidentified Signal Source(USS) Event",
      "type" : "string",
      "examples" : [ "$USS_Type_Salvage;", "$USS_Type_NonHuman;", "$USS_Type_WeaponsFire;" ]
    },
    "USSType_Localised" : {
      "title" : "USSType_Localised",
      "description": "If a Unidentified Signal Source(USS) Event",
      "type" : "string",
      "examples" : [ "Degraded emissions", "Nonhuman signal source", "Weapons fire" ]
    },
    "SpawningState" : {
      "title" : "SpawningState",
      "description": "the BGS state that triggered this event, if relevant",
      "type" : "string",
      "examples" : [ "$FactionState_None;", "$FactionState_CivilUnrest_desc;", "" ]
    },
    "SpawningState_Localised" : {
      "title" : "SpawningState_Localised",
      "type" : "string",
      "examples" : [ "None", "A period of civil unrest represents a failure in local security leading to riots, looting and terrorist activity.", "Expansion represents a factions intention to spread into a nearby system in the near future." ]
    },
    "SpawningFaction" : {
      "title" : "SpawningFaction",
      "description": "the minor faction, if relevant",
      "type" : "string",
      "examples" : [ "$faction_none;", "I.P.S.A.L Project", "Janus Incorporated" ]
    },
    "SpawningFaction_Localised" : {
      "title" : "SpawningFaction_Localised",
      "type" : "string",
      "examples" : [ "None" ]
    },
    "SpawningPower" : {
      "title" : "SpawningPower",
      "description": "the spawning power, if relevant",
      "type" : "string",
      "examples" : [ "Archon Delaine" ]
    },
    "ThreatLevel" : {
      "title" : "ThreatLevel",
      "description": "If a Unidentified Signal Source(USS) Event",
      "type" : "integer",
      "examples" : [ 0, 5, 4 ]
    },
    "TimeRemaining" : {
      "title" : "TimeRemaining",
      "description": "remaining lifetime in seconds, if relevant",
      "type" : "number",
      "examples" : [ 342.042999, 95.250122, 1762.713013 ]
    }
  },
  "additionalProperties" : false,
  "required" : [ "SystemAddress", "SignalName" ]
}