{
  "$schema" : "https://json-schema.org/draft/2020-12/schema",
  "type" : "object",
  "description": "When written: when collecting powerplay commodities for delivery",
  "extends" : { "$ref": "Event.json" },
  "properties" : {
    "Power" : {
      "title" : "Power",
      "type" : "string",
      "examples" : [ "Li Yong-Rui", "Aisling Duval", "Edmund Mahon" ]
    },
    "Type" : {
      "title" : "Type",
      "type" : "string",
      "examples" : [ "$siriusfranchisepackage_name;", "$aislingmediamaterials_name;", "$alliancelegaslativerecords_name;" ]
    },
    "Type_Localised" : {
      "title" : "Type_Localised",
      "type" : "string",
      "examples" : [ "Sirius Franchise Package", "Aisling Media Materials", "Alliance Legislative Records" ]
    },
    "Count" : {
      "title" : "Count",
      "type" : "integer",
      "examples" : [ 10, 50, 44 ]
    }
  },
  "additionalProperties" : false,
  "required" : [ "Power", "Type", "Count" ]
}